CHANGES.txt
LICENSE.txt
MANIFEST.in
README.txt
setup.py
PyWhile.egg-info/PKG-INFO
PyWhile.egg-info/SOURCES.txt
PyWhile.egg-info/dependency_links.txt
PyWhile.egg-info/requires.txt
PyWhile.egg-info/top_level.txt
bin/while.py
docs/01installation.txt
docs/02HelloWorld.txt
docs/03Advanced.txt
docs/04MetaProgramming.txt
pywhile/__init__.py
pywhile/ast.py
pywhile/collectors.py
pywhile/exceptions.py
pywhile/executor.py
pywhile/output.py
pywhile/parser.py