Metadata-Version: 1.0
Name: PyWhile
Version: 0.1.7
Summary: Implementation of the WHILE programming language for computabiliy introductions.
Home-page: UNKNOWN
Author: Aaron Karper
Author-email: maergil@gmail.com
License: LICENSE.txt
Platform: UNKNOWN
